batchtools/__init__.py
batchtools/_version.py
batchtools/check_status.py
batchtools/cli.py
batchtools/submit_subjects.py
batchtools/tests/__init__.py
batchtools/tests/conftest.py
batchtools-0.1.0.dist-info/LICENSE
batchtools-0.1.0.dist-info/METADATA
batchtools-0.1.0.dist-info/WHEEL
batchtools-0.1.0.dist-info/entry_points.txt
batchtools-0.1.0.dist-info/top_level.txt
batchtools-0.1.0.dist-info/RECORD
