Metadata-Version: 2.1
Name: batchtools
Version: 0.1.0
Summary: Command line tool to process subjects with re:THINQ using AWS Batch
Home-page: https://github.com/corticometrics/batchtools
Author: CorticoMetrics, LLC
Author-email: ltirrell@corticometrics.com
License: BSD (3-clause)
Platform: UNKNOWN
Classifier: Development Status :: 2 - Pre-Alpha
Classifier: Natural Language :: English
Classifier: Programming Language :: Python :: 3
Requires-Dist: aiobotocore[awscli] (==1.1.2)
Requires-Dist: boto3 (==1.14.44)
Requires-Dist: click
Requires-Dist: pandas
Requires-Dist: s3fs (==0.5.1)
